xplc/__init__.py
xplc/__main__.py
xplc-0.9.dist-info/entry_points.txt
xplc-0.9.dist-info/LICENSE
xplc-0.9.dist-info/WHEEL
xplc-0.9.dist-info/METADATA
xplc-0.9.dist-info/RECORD
