Metadata-Version: 2.1
Name: xplc
Version: 0.9
Summary: Xplc utilite.
Author-email: xioru team <anikeew@gmail.com>
Requires-Python: >=3.12
Classifier: License :: OSI Approved :: MIT License
Requires-Dist: typer
